sast_secureai/__init__.py
sast_secureai/main.py
sast_secureai/prompts.py
sast_secureai-2025.12.21084550.dist-info/METADATA
sast_secureai-2025.12.21084550.dist-info/WHEEL
sast_secureai-2025.12.21084550.dist-info/top_level.txt
sast_secureai-2025.12.21084550.dist-info/RECORD
