Metadata-Version: 2.4
Name: sast-secureai
Version: 2025.12.21084550
Summary: Automates Software Security Analysis and Testing (SAST) by receiving user-inputted code snippets or text descriptions of functionality and returning a structured response highlighting potential securi
Author-email: sast-secureai <hi@eugene.plus>
License: MIT
Project-URL: Homepage, https://github.com/chigwell/sast-secureai
Requires-Python: >=3.9
Requires-Dist: langchain-llm7>=0.0.0
Requires-Dist: llmatch-messages>=0.0.0
Requires-Dist: langchain-core>=0.3.0
